{
  "project_info": {
    "project_number": "480875746139",
    "firebase_url": "https://learncargo.firebaseio.com",
    "project_id": "learncargo",
    "storage_bucket": "learncargo.appspot.com"
  },
  "client": [
    {
      "client_info": {
        "mobilesdk_app_id": "1:480875746139:android:0d2f23613428572806407e",
        "android_client_info": {
          "package_name": "kg.gruzovoz"
        }
      },
      "oauth_client": [
        {
          "client_id": "480875746139-044334a1c3e62i5j6kiujvals0498jos.apps.googleusercontent.com",
          "client_type": 1,
          "android_info": {
            "package_name": "kg.gruzovoz",
            "certificate_hash": "32780265094515c6dcf5d6507e2d28bae4aea722"
          }
        },
        {
          "client_id": "480875746139-jd77pt0pp1bbm5q9t8bd626qcv7l1fv0.apps.googleusercontent.com",
          "client_type": 3
        }
      ],
      "api_key": [
        {
          "current_key": "AIzaSyAgPGpyBC6Sw8fgXnc86lFhJUmU25nEyyY"
        }
      ],
      "services": {
        "appinvite_service": {
          "other_platform_oauth_client": [
            {
              "client_id": "480875746139-jd77pt0pp1bbm5q9t8bd626qcv7l1fv0.apps.googleusercontent.com",
              "client_type": 3
            }
          ]
        }
      }
    }
  ],
  "configuration_version": "1"
}